{
  "$schema": "https://raw.githubusercontent.com/LGUG2Z/komorebi/v0.1.35/schema.json",
  "app_specific_configuration_path": "$Env:USERPROFILE/applications.json",
  "window_hiding_behaviour": "Cloak",
  "animation": {
    "enabled":true,
  "duration": 200,
  "fps": 60,
  "style": "EaseInOutSine"
  },
  "transparency": false,
  "transparency_alpha": 225,
  "cross_monitor_move_behaviour": "Insert",
  "default_workspace_padding": 5,
  "default_container_padding": 5,
  "border": true,
  "border_width": 3,
  "border_offset": -1,
  "theme": {
    "palette": "Base16",
    "name": "Ashes",
    "unfocused_border": "Base03",
    "bar_accent": "Base0D"
  },
  "stackbar": {
    "height": 40,
    "mode": "OnStack",
    "tabs": {
      "width": 300
    }
  },
  "monitors": [
    {
      "workspaces": [
        {
          "name": "I",
          "layout": "BSP"
        },
        {
          "name": "II",
          "layout": "VerticalStack"
        },
        {
          "name": "III",
          "layout": "HorizontalStack"
        },
        {
          "name": "IV",
          "layout": "UltrawideVerticalStack"
        },
        {
          "name": "V",
          "layout": "Rows"
        },
        {
          "name": "VI",
          "layout": "Grid"
        },
        {
          "name": "VII",
          "layout": "RightMainVerticalStack"
        },
        {
          "name": "VIII",
          "layout": "Columns"
        }
      ]
    }
  ],
  "ignore_rules": [
    {
      "kind": "Exe",
      "matching_strategy": "Equals",
      "id": "Photoshop.exe"
    },
    {
      "kind": "Exe",
      "matching_strategy": "Equals",
      "id": "InDesign.exe"
    },
    {
      "kind": "Exe",
      "matching_strategy": "Equals",
      "id": "Illustrator.exe"
    },
    {
      "kind": "Exe",
      "matching_strategy": "Equals",
      "id": "Acrobat.exe"
    },
    {
      "kind": "Exe",
      "matching_strategy": "Equals",
      "id": "CorelDRAW.exe"
    },
    {
      "kind": "Exe",
      "matching_strategy": "Equals",
      "id": "Figma.exe"
    },
    {
      "kind": "Exe",
      "matching_strategy": "Equals",
      "id": "Spotlightify.exe"
    },
    {
      "kind": "Title",
      "matching_strategy": "Contains",
      "id": "Pasteboard"
    },
    {
      "kind": "Title",
      "matching_strategy": "Contains",
      "id": "AB Download Manager"
    },
    {
      "kind": "Exe",
      "matching_strategy": "Equals",
      "id": "WinRAR.exe"
    },
    {
      "kind": "Title",
      "matching_strategy": "Contains",
      "id": "WHKD Keybinds"
    },
    {
      "kind": "Exe",
      "matching_strategy": "Equals",
      "id": "pot.exe"
    },
    {
      "kind": "Exe",
      "matching_strategy": "Contains",
      "id": "pdfeditor.exe"
    },
    {
      "kind": "Exe",
      "matching_strategy": "Contains",
      "id": "brisk.exe"
    },
    {
      "kind": "Exe",
      "matching_strategy": "Contains",
      "id": "wnr.exe"
    },
    {
      "kind": "Title",
      "matching_strategy": "Contains",
      "id": "Picture in picture"
    },
    {
      "kind": "Title",
      "matching_strategy": "Contains",
      "id": "Calculadora"
    }
  ],
  "floating_applications": [
    {
      "kind": "Class",
      "id": "Photoshop"
    },
    {
      "kind": "Exe",
      "matching_strategy": "Contains",
      "id": "InDesign.exe"
    },
    {
      "kind": "Class",
      "id": "illustrator"
    },
    {
      "kind": "Exe",
      "matching_strategy": "Contains",
      "id": "Acrobat.exe"
    },
    {
      "kind": "Class",
      "matching_strategy": "Contains",
      "id": "CorelDRAW"
    },
    {
      "kind": "Exe",
      "id": "Figma.exe"
    },
    {
      "kind": "Exe",
      "id": "Spotlightify.exe"
    },
    {
      "kind": "Title",
      "matching_strategy": "Contains",
      "id": "Pasteboard"
    },
    {
      "kind": "Exe",
      "id": "ABDownloadManager.exe"
    },
    {
      "kind": "Exe",
      "id": "WinRAR.exe"
    },
    {
      "kind": "Title",
      "id": "WHKD Keybinds"
    },
    {
      "kind": "Exe",
      "matching_strategy": "Equals",
      "id": "pot.exe"
    },
    {
      "kind": "Exe",
      "matching_strategy": "Equals",
      "id": "pdfeditor.exe"
    },
    {
      "kind": "Exe",
      "matching_strategy": "Equals",
      "id": "brisk.exe"
    },
    {
      "kind": "Exe",
      "matching_strategy": "Equals",
      "id": "wnr.exe"
    },
    {
      "kind": "Title",
      "matching_strategy": "Contains",
      "id": "Picture in picture"
    },
    {
      "kind": "Title",
      "matching_strategy": "Contains",
      "id": "Calculadora"
    }
    ]
}
